inspinet_excel/__init__.py
inspinet_excel/inspinet_excel.py
inspinetexcel-0.0.2.dist-info/LICENSE
inspinetexcel-0.0.2.dist-info/METADATA
inspinetexcel-0.0.2.dist-info/WHEEL
inspinetexcel-0.0.2.dist-info/top_level.txt
inspinetexcel-0.0.2.dist-info/RECORD
