Metadata-Version: 2.1
Name: inspinetexcel
Version: 0.0.2
Summary: A set of functions to help dealing with Excel
Home-page: https://github.com/pypa/inspinet_excel
Author: Sebastian Butowski
Author-email: seb@inspinet.co.uk
License: UNKNOWN
Project-URL: Bug Tracker, https://github.com/pypa/inspinet_excel/issues
Platform: UNKNOWN
Classifier: Programming Language :: Python :: 3
Classifier: License :: OSI Approved :: MIT License
Classifier: Operating System :: OS Independent
Requires-Python: >=3.6
License-File: LICENSE
